{
  "Typekit": {
    "description": "Typekit is an online service which offers a subscription library of fonts.",
    "html": [
      { "regex": "<link [^>]*href=\"[^\"]+use\\.typekit\\.(?:net|com)" }
    ],
    "url": [
      {
        "regex": "use\\.typekit\\.net"
      },
      {
        "regex": "use\\.typekit\\.com"
      }
    ],
    "scriptSrc": [
      {
        "regex": "use\\.typekit\\.net"
      },
      {
        "regex": "use\\.typekit\\.com"
      }
    ],
    "website": "https://typekit.com"
  },
  "SquareSpace": {
    "description": "Squarespace provides Software-as-a-Service (SaaS) for website building and hosting, and allows users to use pre-built website templates.",
    "headers": {
      "server": [{ "regex": "Squarespace" }]
    },
    "website": "http://www.squarespace.com",
    "scriptSrc": [{
        "regex": "assets\\.squarespace\\.com"
    }]
  },
  "Nginx": {
    "description": "Nginx is a web server that can also be used as a reverse proxy, load balancer, mail proxy and HTTP cache.",
    "headers": {
      "server": [{"regex": "nginx(?:/([\\d.]+))?"}],
      "X-Fastcgi-Cache": ""
    },
    "website": "https://nginx.org/en"
  },
  "Google Font API": {
    "description": "Google Font API is a web service that supports open-source font files that can be used on your web designs.",
    "scriptSrc": [{"regex": "googleapis\\.com/.+webfont"}],
    "website": "https://google.com/fonts",
    "link": {
        "href": [{"regex": "fonts\\.(?:googleapis|google|gstatic)\\.com"}]
    }
  }
}